TurretIO.py
TurretIO-0.2.dist-info/DESCRIPTION.rst
TurretIO-0.2.dist-info/METADATA
TurretIO-0.2.dist-info/metadata.json
TurretIO-0.2.dist-info/RECORD
TurretIO-0.2.dist-info/top_level.txt
TurretIO-0.2.dist-info/WHEEL
