Metadata-Version: 2.0
Name: TurretIO
Version: 0.2
Summary: Turret.IO Python client library
Home-page: http://turret.io
Author: Turret IO Team
Author-email: team@turret.io
License: UNKNOWN
Keywords: Turret.IO,turretio,email marketing
Platform: UNKNOWN
Requires-Dist: requests
